LICENSE
MANIFEST.in
README.rst
requirements.txt
setup.cfg
setup.py
aprs/__init__.py
aprs/classes.py
aprs/constants.py
aprs/decimaldegrees.py
aprs/exceptions.py
aprs/fcs.py
aprs/functions.py
aprs/geo_util.py
aprs/kiss_classes.py
aprs/util.py
aprs.egg-info/PKG-INFO
aprs.egg-info/SOURCES.txt
aprs.egg-info/dependency_links.txt
aprs.egg-info/not-zip-safe
aprs.egg-info/requires.txt
aprs.egg-info/top_level.txt