Metadata-Version: 1.1
Name: aprs
Version: 7.0.0
Summary: Python APRS Module.
Home-page: https://github.com/ampledata/aprs
Author: Greg Albrecht
Author-email: oss@undef.net
License: Copyright 2017 Greg Albrecht and Contributors
